spotiapi.py
spotiapi-2.0.3.dist-info/LICENSE
spotiapi-2.0.3.dist-info/WHEEL
spotiapi-2.0.3.dist-info/METADATA
spotiapi-2.0.3.dist-info/RECORD
